[
    {
        "card_name": "Visage of Emeria",
        "number": 31,
        "shape": "normal",
        "set": "BYK",
        "position": "31"
    },
    {
        "card_name": "Bearer of Silk Chains",
        "number": 33,
        "shape": "normal",
        "set": "BYK",
        "position": "33"
    },
    {
        "card_name": "Kalemn, Bound by Violence",
        "number": 70,
        "shape": "normal",
        "set": "BYK",
        "position": "70"
    },
    {
        "card_name": "Dawn Without End",
        "number": 95,
        "shape": "normal",
        "set": "BYK",
        "position": "95"
    },
    {
        "card_name": "Ashka Ritualist",
        "number": 121,
        "shape": "normal",
        "set": "BYK",
        "position": "121"
    },
    {
        "card_name": "Born Anew",
        "number": 5,
        "shape": "normal",
        "set": "BYK",
        "position": "5"
    },
    {
        "card_name": "Collector of Memories",
        "number": 35,
        "shape": "normal",
        "set": "BYK",
        "position": "35"
    },
    {
        "card_name": "Black Hole Musings",
        "number": 62,
        "shape": "normal",
        "set": "BYK",
        "position": "62"
    },
    {
        "card_name": "Everember Phoenix",
        "number": 98,
        "shape": "normal",
        "set": "BYK",
        "position": "98"
    },
    {
        "card_name": "Beckon the Pack",
        "number": 123,
        "shape": "normal",
        "set": "BYK",
        "position": "123"
    },
    {
        "card_name": "Bringer of Blessed Ends",
        "number": 6,
        "shape": "normal",
        "set": "BYK",
        "position": "6"
    },
    {
        "card_name": "Drown Amidst the Cosmos",
        "number": 38,
        "shape": "normal",
        "set": "BYK",
        "position": "38"
    },
    {
        "card_name": "Brink of Something",
        "number": 64,
        "shape": "normal",
        "set": "BYK",
        "position": "64"
    },
    {
        "card_name": "Grasp for Understanding",
        "number": 102,
        "shape": "normal",
        "set": "BYK",
        "position": "102"
    },
    {
        "card_name": "Blessed Piper",
        "number": 125,
        "shape": "normal",
        "set": "BYK",
        "position": "125"
    },
    {
        "card_name": "Fleshscale Serpent",
        "number": 14,
        "shape": "normal",
        "set": "BYK",
        "position": "14"
    },
    {
        "card_name": "Elusive Hunter",
        "number": 39,
        "shape": "normal",
        "set": "BYK",
        "position": "39"
    },
    {
        "card_name": "Hungering Cult",
        "number": 68,
        "shape": "normal",
        "set": "BYK",
        "position": "68"
    },
    {
        "card_name": "Harvest Flesh",
        "number": 103,
        "shape": "normal",
        "set": "BYK",
        "position": "103"
    },
    {
        "card_name": "Breach the Lilies",
        "number": 126,
        "shape": "normal",
        "set": "BYK",
        "position": "126"
    },
    {
        "card_name": "Gleaming Elf",
        "number": 15,
        "shape": "normal",
        "set": "BYK",
        "position": "15"
    },
    {
        "card_name": "Fate Takes its Course",
        "number": 42,
        "shape": "normal",
        "set": "BYK",
        "position": "42"
    },
    {
        "card_name": "Infectious Ego",
        "number": 69,
        "shape": "normal",
        "set": "BYK",
        "position": "69"
    },
    {
        "card_name": "Ironhide Bellower",
        "number": 107,
        "shape": "normal",
        "set": "BYK",
        "position": "107"
    },
    {
        "card_name": "Destiny Beyond Measure",
        "number": 129,
        "shape": "normal",
        "set": "BYK",
        "position": "129"
    },
    {
        "card_name": "Hallowed Moon Sentinel",
        "number": 16,
        "shape": "normal",
        "set": "BYK",
        "position": "16"
    },
    {
        "card_name": "Feathered Oracle",
        "number": 43,
        "shape": "normal",
        "set": "BYK",
        "position": "43"
    },
    {
        "card_name": "Obey",
        "number": 75,
        "shape": "normal",
        "set": "BYK",
        "position": "75"
    },
    {
        "card_name": "Masha Ritualist",
        "number": 109,
        "shape": "normal",
        "set": "BYK",
        "position": "109"
    },
    {
        "card_name": "Reconstruct_BYK",
        "number": 137,
        "shape": "normal",
        "set": "BYK",
        "position": "137"
    },
    {
        "card_name": "Legion Angel",
        "number": 22,
        "shape": "normal",
        "set": "BYK",
        "position": "22"
    },
    {
        "card_name": "Fold Will",
        "number": 44,
        "shape": "normal",
        "set": "BYK",
        "position": "44"
    },
    {
        "card_name": "Reduce to Naught",
        "number": 79,
        "shape": "normal",
        "set": "BYK",
        "position": "79"
    },
    {
        "card_name": "Molten Agitator",
        "number": 110,
        "shape": "normal",
        "set": "BYK",
        "position": "110"
    },
    {
        "card_name": "Shapen, Spiteful Creation",
        "number": 139,
        "shape": "normal",
        "set": "BYK",
        "position": "139"
    },
    {
        "card_name": "Pull Away",
        "number": 24,
        "shape": "normal",
        "set": "BYK",
        "position": "24"
    },
    {
        "card_name": "From Stars Above",
        "number": 45,
        "shape": "normal",
        "set": "BYK",
        "position": "45"
    },
    {
        "card_name": "Setar Ritualist",
        "number": 80,
        "shape": "normal",
        "set": "BYK",
        "position": "80"
    },
    {
        "card_name": "Silver-Dawn Radiant",
        "number": 113,
        "shape": "normal",
        "set": "BYK",
        "position": "113"
    },
    {
        "card_name": "Shapen's Taunts",
        "number": 140,
        "shape": "normal",
        "set": "BYK",
        "position": "140"
    },
    {
        "card_name": "Roya Ritualist",
        "number": 25,
        "shape": "normal",
        "set": "BYK",
        "position": "25"
    },
    {
        "card_name": "Helar Ritualist",
        "number": 47,
        "shape": "normal",
        "set": "BYK",
        "position": "47"
    },
    {
        "card_name": "A Sight Too Far",
        "number": 81,
        "shape": "normal",
        "set": "BYK",
        "position": "81"
    },
    {
        "card_name": "Solar Hatching",
        "number": 116,
        "shape": "normal",
        "set": "BYK",
        "position": "116"
    },
    {
        "card_name": "Silver-Dawn Elder",
        "number": 142,
        "shape": "normal",
        "set": "BYK",
        "position": "142"
    },
    {
        "card_name": "Speaker of Deliverance",
        "number": 26,
        "shape": "normal",
        "set": "BYK",
        "position": "26"
    },
    {
        "card_name": "Sinewed Wings",
        "number": 55,
        "shape": "normal",
        "set": "BYK",
        "position": "55"
    },
    {
        "card_name": "Still-Smoke Skirmisher",
        "number": 83,
        "shape": "normal",
        "set": "BYK",
        "position": "83"
    },
    {
        "card_name": "Stubborn Blademate",
        "number": 117,
        "shape": "normal",
        "set": "BYK",
        "position": "117"
    },
    {
        "card_name": "Silver-Dawn Ranger",
        "number": 143,
        "shape": "normal",
        "set": "BYK",
        "position": "143"
    },
    {
        "card_name": "Vashi, Twin-Star Paragon",
        "number": 30,
        "shape": "normal",
        "set": "BYK",
        "position": "30"
    },
    {
        "card_name": "Succumb to Dreams",
        "number": 56,
        "shape": "normal",
        "set": "BYK",
        "position": "56"
    },
    {
        "card_name": "Still-Smoke Stitcher",
        "number": 84,
        "shape": "normal",
        "set": "BYK",
        "position": "84"
    },
    {
        "card_name": "These Final Moments",
        "number": 118,
        "shape": "normal",
        "set": "BYK",
        "position": "118"
    },
    {
        "card_name": "World Made Anew",
        "number": 149,
        "shape": "normal",
        "set": "BYK",
        "position": "149"
    },
    {
        "card_name": "Witness the Divine",
        "number": 32,
        "shape": "normal",
        "set": "BYK",
        "position": "32"
    },
    {
        "card_name": "Corrupted Soothsayer",
        "number": 36,
        "shape": "normal",
        "set": "BYK",
        "position": "36"
    },
    {
        "card_name": "Tahli, Twin-Star Seer",
        "number": 85,
        "shape": "normal",
        "set": "BYK",
        "position": "85"
    },
    {
        "card_name": "Annihilation",
        "number": 92,
        "shape": "normal",
        "set": "BYK",
        "position": "92"
    },
    {
        "card_name": "Beyond All Horizons",
        "number": 124,
        "shape": "normal",
        "set": "BYK",
        "position": "124"
    },
    {
        "card_name": "Abjuration Savant",
        "number": 3,
        "shape": "normal",
        "set": "BYK",
        "position": "3"
    },
    {
        "card_name": "Cursory Glance_BYK",
        "number": 37,
        "shape": "normal",
        "set": "BYK",
        "position": "37"
    },
    {
        "card_name": "Death Kneels Before",
        "number": 65,
        "shape": "normal",
        "set": "BYK",
        "position": "65"
    },
    {
        "card_name": "Cackling Seer",
        "number": 94,
        "shape": "normal",
        "set": "BYK",
        "position": "94"
    },
    {
        "card_name": "Pieces of Creation",
        "number": 136,
        "shape": "normal",
        "set": "BYK",
        "position": "136"
    },
    {
        "card_name": "Ashkan Preserver",
        "number": 4,
        "shape": "normal",
        "set": "BYK",
        "position": "4"
    },
    {
        "card_name": "Embrace of Mist",
        "number": 40,
        "shape": "normal",
        "set": "BYK",
        "position": "40"
    },
    {
        "card_name": "Litany of Fallen Blades",
        "number": 71,
        "shape": "normal",
        "set": "BYK",
        "position": "71"
    },
    {
        "card_name": "Faith Burns Brightest",
        "number": 99,
        "shape": "normal",
        "set": "BYK",
        "position": "99"
    },
    {
        "card_name": "Remnant of the Hunt",
        "number": 138,
        "shape": "normal",
        "set": "BYK",
        "position": "138"
    },
    {
        "card_name": "Clarity of Self",
        "number": 7,
        "shape": "normal",
        "set": "BYK",
        "position": "7"
    },
    {
        "card_name": "Give Penance",
        "number": 46,
        "shape": "normal",
        "set": "BYK",
        "position": "46"
    },
    {
        "card_name": "Reclusive Augur",
        "number": 78,
        "shape": "normal",
        "set": "BYK",
        "position": "78"
    },
    {
        "card_name": "Gentle Repose",
        "number": 101,
        "shape": "normal",
        "set": "BYK",
        "position": "101"
    },
    {
        "card_name": "Still-Smoke Oracle",
        "number": 144,
        "shape": "normal",
        "set": "BYK",
        "position": "144"
    },
    {
        "card_name": "Disassociate_BYK",
        "number": 9,
        "shape": "normal",
        "set": "BYK",
        "position": "9"
    },
    {
        "card_name": "Mirror Reality",
        "number": 48,
        "shape": "normal",
        "set": "BYK",
        "position": "48"
    },
    {
        "card_name": "Still-Smoke Hunter",
        "number": 82,
        "shape": "normal",
        "set": "BYK",
        "position": "82"
    },
    {
        "card_name": "Illusory Stag",
        "number": 105,
        "shape": "normal",
        "set": "BYK",
        "position": "105"
    },
    {
        "card_name": "Swarm of Sporemites",
        "number": 145,
        "shape": "normal",
        "set": "BYK",
        "position": "145"
    },
    {
        "card_name": "Fade",
        "number": 12,
        "shape": "normal",
        "set": "BYK",
        "position": "12"
    },
    {
        "card_name": "Through Shattered Senses",
        "number": 57,
        "shape": "normal",
        "set": "BYK",
        "position": "57"
    },
    {
        "card_name": "Understand Desolation",
        "number": 88,
        "shape": "normal",
        "set": "BYK",
        "position": "88"
    },
    {
        "card_name": "Slithering Eyes",
        "number": 115,
        "shape": "normal",
        "set": "BYK",
        "position": "115"
    },
    {
        "card_name": "Thriving Shaman",
        "number": 146,
        "shape": "normal",
        "set": "BYK",
        "position": "146"
    },
    {
        "card_name": "Heavens Held Waiting",
        "number": 19,
        "shape": "normal",
        "set": "BYK",
        "position": "19"
    },
    {
        "card_name": "A Vision Too Vast",
        "number": 59,
        "shape": "normal",
        "set": "BYK",
        "position": "59"
    },
    {
        "card_name": "Weeping Whisperer",
        "number": 90,
        "shape": "normal",
        "set": "BYK",
        "position": "90"
    },
    {
        "card_name": "While Blood Still Flows",
        "number": 119,
        "shape": "normal",
        "set": "BYK",
        "position": "119"
    },
    {
        "card_name": "Walker of the Final Path",
        "number": 147,
        "shape": "normal",
        "set": "BYK",
        "position": "147"
    },
    {
        "card_name": "Subdue False Idols",
        "number": 27,
        "shape": "normal",
        "set": "BYK",
        "position": "27"
    },
    {
        "card_name": "Become Nothing",
        "number": 34,
        "shape": "normal",
        "set": "BYK",
        "position": "34"
    },
    {
        "card_name": "World Torn Asunder",
        "number": 91,
        "shape": "normal",
        "set": "BYK",
        "position": "91"
    },
    {
        "card_name": "Blooming Martyr",
        "number": 93,
        "shape": "normal",
        "set": "BYK",
        "position": "93"
    },
    {
        "card_name": "Ashka's Hunter",
        "number": 122,
        "shape": "normal",
        "set": "BYK",
        "position": "122"
    },
    {
        "card_name": "Crystallized Hope_BYK",
        "number": 8,
        "shape": "normal",
        "set": "BYK",
        "position": "8"
    },
    {
        "card_name": "Ethereal Sneak",
        "number": 41,
        "shape": "normal",
        "set": "BYK",
        "position": "41"
    },
    {
        "card_name": "Blinded Necromancer",
        "number": 63,
        "shape": "normal",
        "set": "BYK",
        "position": "63"
    },
    {
        "card_name": "Drenched in Triumph",
        "number": 96,
        "shape": "normal",
        "set": "BYK",
        "position": "96"
    },
    {
        "card_name": "Canopy Dancer",
        "number": 127,
        "shape": "normal",
        "set": "BYK",
        "position": "127"
    },
    {
        "card_name": "Do No Evil",
        "number": 10,
        "shape": "normal",
        "set": "BYK",
        "position": "10"
    },
    {
        "card_name": "Mishka's Conjuring",
        "number": 49,
        "shape": "normal",
        "set": "BYK",
        "position": "49"
    },
    {
        "card_name": "Hadik's Striker",
        "number": 66,
        "shape": "normal",
        "set": "BYK",
        "position": "66"
    },
    {
        "card_name": "Essence Carver",
        "number": 97,
        "shape": "normal",
        "set": "BYK",
        "position": "97"
    },
    {
        "card_name": "Crooked Growth",
        "number": 128,
        "shape": "normal",
        "set": "BYK",
        "position": "128"
    },
    {
        "card_name": "Ethereal Runner",
        "number": 11,
        "shape": "normal",
        "set": "BYK",
        "position": "11"
    },
    {
        "card_name": "Mnemonic Wall",
        "number": 50,
        "shape": "normal",
        "set": "BYK",
        "position": "50"
    },
    {
        "card_name": "Hollyberry Murder",
        "number": 67,
        "shape": "normal",
        "set": "BYK",
        "position": "67"
    },
    {
        "card_name": "Firefish Conjurer",
        "number": 100,
        "shape": "normal",
        "set": "BYK",
        "position": "100"
    },
    {
        "card_name": "Fauna Tender",
        "number": 130,
        "shape": "normal",
        "set": "BYK",
        "position": "130"
    },
    {
        "card_name": "Flesh Willing",
        "number": 13,
        "shape": "normal",
        "set": "BYK",
        "position": "13"
    },
    {
        "card_name": "Monokeros Rider",
        "number": 51,
        "shape": "normal",
        "set": "BYK",
        "position": "51"
    },
    {
        "card_name": "The Mind Falters",
        "number": 72,
        "shape": "normal",
        "set": "BYK",
        "position": "72"
    },
    {
        "card_name": "Heavenly Fire",
        "number": 104,
        "shape": "normal",
        "set": "BYK",
        "position": "104"
    },
    {
        "card_name": "From Unbidden Realms",
        "number": 131,
        "shape": "normal",
        "set": "BYK",
        "position": "131"
    },
    {
        "card_name": "Heavenly Emergence",
        "number": 17,
        "shape": "normal",
        "set": "BYK",
        "position": "17"
    },
    {
        "card_name": "Pull from Beyond",
        "number": 52,
        "shape": "normal",
        "set": "BYK",
        "position": "52"
    },
    {
        "card_name": "Misery Keeps Company",
        "number": 73,
        "shape": "normal",
        "set": "BYK",
        "position": "73"
    },
    {
        "card_name": "Incandescent Matron",
        "number": 106,
        "shape": "normal",
        "set": "BYK",
        "position": "106"
    },
    {
        "card_name": "Gift to Finality",
        "number": 132,
        "shape": "normal",
        "set": "BYK",
        "position": "132"
    },
    {
        "card_name": "Heavens Claim Their Due",
        "number": 18,
        "shape": "normal",
        "set": "BYK",
        "position": "18"
    },
    {
        "card_name": "Seeker of Communions",
        "number": 53,
        "shape": "normal",
        "set": "BYK",
        "position": "53"
    },
    {
        "card_name": "Moth-Heart Husk",
        "number": 74,
        "shape": "normal",
        "set": "BYK",
        "position": "74"
    },
    {
        "card_name": "Martial Mastery",
        "number": 108,
        "shape": "normal",
        "set": "BYK",
        "position": "108"
    },
    {
        "card_name": "Ichorsap Dryad",
        "number": 133,
        "shape": "normal",
        "set": "BYK",
        "position": "133"
    },
    {
        "card_name": "Helar's Sanctifier",
        "number": 20,
        "shape": "normal",
        "set": "BYK",
        "position": "20"
    },
    {
        "card_name": "Serene Hart",
        "number": 54,
        "shape": "normal",
        "set": "BYK",
        "position": "54"
    },
    {
        "card_name": "Overwhelming Guilt_BYK",
        "number": 76,
        "shape": "normal",
        "set": "BYK",
        "position": "76"
    },
    {
        "card_name": "Settlement Scout",
        "number": 111,
        "shape": "normal",
        "set": "BYK",
        "position": "111"
    },
    {
        "card_name": "Lotusleaf Blade",
        "number": 134,
        "shape": "normal",
        "set": "BYK",
        "position": "134"
    },
    {
        "card_name": "Immaculate Choir",
        "number": 21,
        "shape": "normal",
        "set": "BYK",
        "position": "21"
    },
    {
        "card_name": "Time Flows to Its End",
        "number": 58,
        "shape": "normal",
        "set": "BYK",
        "position": "58"
    },
    {
        "card_name": "Piece by Piece",
        "number": 77,
        "shape": "normal",
        "set": "BYK",
        "position": "77"
    },
    {
        "card_name": "Shapen's Cruelty",
        "number": 112,
        "shape": "normal",
        "set": "BYK",
        "position": "112"
    },
    {
        "card_name": "Mortal Deeds",
        "number": 135,
        "shape": "normal",
        "set": "BYK",
        "position": "135"
    },
    {
        "card_name": "Palesoul Mender",
        "number": 23,
        "shape": "normal",
        "set": "BYK",
        "position": "23"
    },
    {
        "card_name": "Watch from Above_BYK",
        "number": 60,
        "shape": "normal",
        "set": "BYK",
        "position": "60"
    },
    {
        "card_name": "Tides of Dust",
        "number": 86,
        "shape": "normal",
        "set": "BYK",
        "position": "86"
    },
    {
        "card_name": "Single-Minded Mob",
        "number": 114,
        "shape": "normal",
        "set": "BYK",
        "position": "114"
    },
    {
        "card_name": "Shepherd of Lonely Souls",
        "number": 141,
        "shape": "normal",
        "set": "BYK",
        "position": "141"
    },
    {
        "card_name": "Twin-Star Herald",
        "number": 28,
        "shape": "normal",
        "set": "BYK",
        "position": "28"
    },
    {
        "card_name": "What Little Remains",
        "number": 61,
        "shape": "normal",
        "set": "BYK",
        "position": "61"
    },
    {
        "card_name": "Tower of Sorrows",
        "number": 87,
        "shape": "normal",
        "set": "BYK",
        "position": "87"
    },
    {
        "card_name": "Worn to Nothing",
        "number": 120,
        "shape": "normal",
        "set": "BYK",
        "position": "120"
    },
    {
        "card_name": "Welcome What Comes",
        "number": 148,
        "shape": "normal",
        "set": "BYK",
        "position": "148"
    },
    {
        "card_name": "Upon Fourfold Wings",
        "number": 29,
        "shape": "normal",
        "set": "BYK",
        "position": "29"
    },
    {
        "card_name": "Elusive Devout",
        "number": 192,
        "shape": "normal",
        "set": "BYK",
        "position": "192"
    },
    {
        "card_name": "Walking Remorse",
        "number": 89,
        "shape": "normal",
        "set": "BYK",
        "position": "89"
    },
    {
        "card_name": "Fervent Devout",
        "number": 194,
        "shape": "normal",
        "set": "BYK",
        "position": "194"
    },
    {
        "card_name": "Feral Devout",
        "number": 193,
        "shape": "normal",
        "set": "BYK",
        "position": "193"
    },
    {
        "card_name": "Lustrous Devout",
        "number": 195,
        "shape": "normal",
        "set": "BYK",
        "position": "195"
    },
    {
        "card_name": "e"
    },
    {
        "card_name": "Poisoned Devout",
        "number": 196,
        "shape": "normal",
        "set": "BYK",
        "position": "196"
    },
    {
        "card_name": "e"
    },
    {
        "card_name": "e"
    },
    {
        "card_name": "er"
    },
    {
        "card_name": "er"
    },
    {
        "card_name": "er"
    },
    {
        "card_name": "er"
    },
    "a->gold",
    {
        "card_name": "Gentle Omens",
        "number": 152,
        "shape": "normal",
        "set": "BYK",
        "position": "152"
    },
    {
        "card_name": "Bearer of Tormented Truths",
        "number": 154,
        "shape": "normal",
        "set": "BYK",
        "position": "154"
    },
    {
        "card_name": "Angel of the Eclipse",
        "number": 158,
        "shape": "normal",
        "set": "BYK",
        "position": "158"
    },
    {
        "card_name": "Hadik, Might of Mortals",
        "number": 164,
        "shape": "normal",
        "set": "BYK",
        "position": "164"
    },
    {
        "card_name": "Endless Helpless Souls_BYK",
        "number": 166,
        "shape": "normal",
        "set": "BYK",
        "position": "166"
    },
    {
        "card_name": "Bind the Mind",
        "number": 150,
        "shape": "normal",
        "set": "BYK",
        "position": "150"
    },
    {
        "card_name": "Keep What Was Lost",
        "number": 155,
        "shape": "normal",
        "set": "BYK",
        "position": "155"
    },
    {
        "card_name": "Give to Sacred Halls",
        "number": 159,
        "shape": "normal",
        "set": "BYK",
        "position": "159"
    },
    {
        "card_name": "Emberheart Witch",
        "number": 162,
        "shape": "normal",
        "set": "BYK",
        "position": "162"
    },
    {
        "card_name": "Seeker of New Truths",
        "number": 168,
        "shape": "normal",
        "set": "BYK",
        "position": "168"
    },
    {
        "card_name": "Skittering Beauty",
        "number": 153,
        "shape": "normal",
        "set": "BYK",
        "position": "153"
    },
    {
        "card_name": "Needless Atrocities",
        "number": 157,
        "shape": "normal",
        "set": "BYK",
        "position": "157"
    },
    {
        "card_name": "Ill-Fated Seer",
        "number": 161,
        "shape": "normal",
        "set": "BYK",
        "position": "161"
    },
    {
        "card_name": "Hadik's Cohort",
        "number": 165,
        "shape": "normal",
        "set": "BYK",
        "position": "165"
    },
    {
        "card_name": "Tandem Glory",
        "number": 169,
        "shape": "normal",
        "set": "BYK",
        "position": "169"
    },
    {
        "card_name": "A Flawless World",
        "number": 151,
        "shape": "normal",
        "set": "BYK",
        "position": "151"
    },
    {
        "card_name": "Lonely Visage",
        "number": 156,
        "shape": "normal",
        "set": "BYK",
        "position": "156"
    },
    {
        "card_name": "Grisly Offering",
        "number": 160,
        "shape": "normal",
        "set": "BYK",
        "position": "160"
    },
    {
        "card_name": "Gilded Bloodsworn",
        "number": 163,
        "shape": "normal",
        "set": "BYK",
        "position": "163"
    },
    {
        "card_name": "Mourn No More",
        "number": 167,
        "shape": "normal",
        "set": "BYK",
        "position": "167"
    },
    {
        "card_name": "er"
    },
    {
        "card_name": "er"
    },
    {
        "card_name": "er"
    },
    {
        "card_name": "er"
    },
    {
        "card_name": "er"
    },
    {
        "card_name": "e"
    },
    {
        "card_name": "e"
    },
    {
        "card_name": "e"
    },
    {
        "card_name": "e"
    },
    {
        "card_name": "Helene, Bound by Might",
        "number": 170,
        "shape": "normal",
        "set": "BYK",
        "position": "170"
    },
    {
        "card_name": "er"
    },
    {
        "card_name": "er"
    },
    {
        "card_name": "er"
    },
    {
        "card_name": "er"
    },
    {
        "card_name": "er"
    },
    {
        "card_name": "Helar's Herald",
        "number": 179,
        "shape": "normal",
        "set": "BYK",
        "position": "179"
    },
    {
        "card_name": "Inflicted Ideals",
        "number": 180,
        "shape": "normal",
        "set": "BYK",
        "position": "180"
    },
    {
        "card_name": "Fortune Dealer",
        "number": 178,
        "shape": "normal",
        "set": "BYK",
        "position": "178"
    },
    {
        "card_name": "Twin-Star Heartweaver",
        "number": 188,
        "shape": "normal",
        "set": "BYK",
        "position": "188"
    },
    {
        "card_name": "End of All Things_BYK",
        "number": 176,
        "shape": "normal",
        "set": "BYK",
        "position": "176"
    },
    {
        "card_name": "Still-Smoke Sojourners",
        "number": 186,
        "shape": "normal",
        "set": "BYK",
        "position": "186"
    },
    {
        "card_name": "Whims of Fate",
        "number": 191,
        "shape": "normal",
        "set": "BYK",
        "position": "191"
    },
    {
        "card_name": "Ravik, Still-Smoke Seer",
        "number": 181,
        "shape": "normal",
        "set": "BYK",
        "position": "181"
    },
    {
        "card_name": "United Focus",
        "number": 189,
        "shape": "normal",
        "set": "BYK",
        "position": "189"
    },
    {
        "card_name": "Shuck Mortal Coils",
        "number": 184,
        "shape": "normal",
        "set": "BYK",
        "position": "184"
    },
    {
        "card_name": "Blessing of Helar",
        "number": 172,
        "shape": "normal",
        "set": "BYK",
        "position": "172"
    },
    {
        "card_name": "Blessing of Setar",
        "number": 174,
        "shape": "normal",
        "set": "BYK",
        "position": "174"
    },
    {
        "card_name": "Fall of Masha",
        "number": 177,
        "shape": "normal",
        "set": "BYK",
        "position": "177"
    },
    {
        "card_name": "Blessing of Ashka",
        "number": 171,
        "shape": "normal",
        "set": "BYK",
        "position": "171"
    },
    {
        "card_name": "Blessing of Roya",
        "number": 173,
        "shape": "normal",
        "set": "BYK",
        "position": "173"
    },
    {
        "card_name": "Unravel Prophecy",
        "number": 190,
        "shape": "normal",
        "set": "BYK",
        "position": "190"
    },
    {
        "card_name": "Cruel Heartbeat",
        "number": 175,
        "shape": "normal",
        "set": "BYK",
        "position": "175"
    },
    {
        "card_name": "Tahli's Council",
        "number": 187,
        "shape": "normal",
        "set": "BYK",
        "position": "187"
    },
    {
        "card_name": "Shifting Brute",
        "number": 183,
        "shape": "normal",
        "set": "BYK",
        "position": "183"
    },
    {
        "card_name": "Song of Shoals",
        "number": 185,
        "shape": "normal",
        "set": "BYK",
        "position": "185"
    },
    {
        "card_name": "er"
    },
    {
        "card_name": "er"
    },
    {
        "card_name": "er"
    },
    {
        "card_name": "er"
    },
    "a->colorless",
    {
        "card_name": "Makshi, Patron of Blades",
        "number": 1,
        "shape": "normal",
        "set": "BYK",
        "position": "1"
    },
    {
        "card_name": "Perception Pool",
        "number": 199,
        "shape": "normal",
        "set": "BYK",
        "position": "199"
    },
    {
        "card_name": "Void Hilt",
        "number": 203,
        "shape": "normal",
        "set": "BYK",
        "position": "203"
    },
    {
        "card_name": "Weeping Lotus",
        "number": 205,
        "shape": "normal",
        "set": "BYK",
        "position": "205"
    },
    {
        "card_name": "Hail of Blades",
        "number": 198,
        "shape": "normal",
        "set": "BYK",
        "position": "198"
    },
    {
        "card_name": "Settlement Guardian",
        "number": 200,
        "shape": "normal",
        "set": "BYK",
        "position": "200"
    },
    {
        "card_name": "Sunderer of Veils",
        "number": 202,
        "shape": "normal",
        "set": "BYK",
        "position": "202"
    },
    {
        "card_name": "Unravel Shattered Worlds",
        "number": 2,
        "shape": "normal",
        "set": "BYK",
        "position": "2"
    },
    {
        "card_name": "Ancestor's Bulwark",
        "number": 197,
        "shape": "normal",
        "set": "BYK",
        "position": "197"
    },
    {
        "card_name": "Shield of the Unwavering",
        "number": 201,
        "shape": "normal",
        "set": "BYK",
        "position": "201"
    },
    {
        "card_name": "Weave Etcher",
        "number": 204,
        "shape": "normal",
        "set": "BYK",
        "position": "204"
    },
    {
        "card_name": "e"
    },
    {
        "card_name": "e"
    },
    {
        "card_name": "e"
    },
    {
        "card_name": "e"
    },
    {
        "card_name": "er"
    },
    {
        "card_name": "er"
    },
    {
        "card_name": "er"
    },
    {
        "card_name": "er"
    },
    {
        "card_name": "er"
    },
    {
        "card_name": "Fields of Worship",
        "number": 206,
        "shape": "normal",
        "set": "BYK",
        "position": "206"
    },
    {
        "card_name": "Inscrutable Realms",
        "number": 207,
        "shape": "normal",
        "set": "BYK",
        "position": "207"
    },
    {
        "card_name": "Inviolable Realms",
        "number": 208,
        "shape": "normal",
        "set": "BYK",
        "position": "208"
    },
    {
        "card_name": "Mortal Realms",
        "number": 209,
        "shape": "normal",
        "set": "BYK",
        "position": "209"
    },
    {
        "card_name": "Tempting Realms",
        "number": 210,
        "shape": "normal",
        "set": "BYK",
        "position": "210"
    },
    {
        "card_name": "Wild Realms",
        "number": 211,
        "shape": "normal",
        "set": "BYK",
        "position": "211"
    },
    {
        "card_name": "e"
    },
    {
        "card_name": "e"
    },
    {
        "card_name": "e"
    },
    {
        "card_name": "e"
    },
    {
        "card_name": "er"
    },
    {
        "card_name": "er"
    },
    {
        "card_name": "er"
    },
    {
        "card_name": "er"
    },
    {
        "card_name": "er"
    }
]